router_tools/__init__.py
router_tools/dns_query.py
router_tools/sample.py
router_tools/test/__init__.py
router_tools/test/test_dns_query.py
router_tools/test/test_sample.py
router_tools-0.1.9.data/scripts/dns_query.py
router_tools-0.1.9.dist-info/DESCRIPTION.rst
router_tools-0.1.9.dist-info/METADATA
router_tools-0.1.9.dist-info/RECORD
router_tools-0.1.9.dist-info/WHEEL
router_tools-0.1.9.dist-info/metadata.json
router_tools-0.1.9.dist-info/top_level.txt
