Metadata-Version: 2.0
Name: router-tools
Version: 0.1.9
Summary: Simple tool for router maintain.
Home-page: https://github.com/renweibo/router_tools
Author: Ren Weibo
Author-email: renweibo@gmail.com
License: MIT License
Platform: UNKNOWN
Classifier: Development Status :: 2 - Pre-Alpha
Classifier: Programming Language :: Python
Classifier: Programming Language :: Python :: 2
Classifier: Programming Language :: Python :: 2.7
Classifier: Programming Language :: Python :: 3
Classifier: Programming Language :: Python :: 3.5
Provides-Extra: testing
Requires-Dist: pytest; extra == 'testing'
